ceilometer_powervm/__init__.py
ceilometer_powervm/version.py
ceilometer_powervm/compute/__init__.py
ceilometer_powervm/compute/virt/__init__.py
ceilometer_powervm/compute/virt/powervm/__init__.py
ceilometer_powervm/compute/virt/powervm/i18n.py
ceilometer_powervm/compute/virt/powervm/inspector.py
ceilometer_powervm/locale/ceilometer-powervm.pot
ceilometer_powervm/locale/de/ceilometer-powervm.po
ceilometer_powervm/locale/es/ceilometer-powervm.po
ceilometer_powervm/locale/fr/ceilometer-powervm.po
ceilometer_powervm/locale/it/ceilometer-powervm.po
ceilometer_powervm/locale/ja/ceilometer-powervm.po
ceilometer_powervm/locale/ko/ceilometer-powervm.po
ceilometer_powervm/locale/pt-BR/ceilometer-powervm.po
ceilometer_powervm/locale/ru/ceilometer-powervm.po
ceilometer_powervm/locale/zh-Hans/ceilometer-powervm.po
ceilometer_powervm/locale/zh-Hant/ceilometer-powervm.po
ceilometer_powervm/tests/__init__.py
ceilometer_powervm/tests/compute/__init__.py
ceilometer_powervm/tests/compute/virt/__init__.py
ceilometer_powervm/tests/compute/virt/powervm/__init__.py
ceilometer_powervm/tests/compute/virt/powervm/pvm_fixtures.py
ceilometer_powervm/tests/compute/virt/powervm/test_inspector.py
ceilometer_powervm-9.0.0.dist-info/AUTHORS
ceilometer_powervm-9.0.0.dist-info/LICENSE
ceilometer_powervm-9.0.0.dist-info/METADATA
ceilometer_powervm-9.0.0.dist-info/WHEEL
ceilometer_powervm-9.0.0.dist-info/entry_points.txt
ceilometer_powervm-9.0.0.dist-info/pbr.json
ceilometer_powervm-9.0.0.dist-info/top_level.txt
ceilometer_powervm-9.0.0.dist-info/RECORD
